titli/__init__.py
titli/backups/kitsune.py
titli/backups/pytorch_kitsune.py
titli/backups/torch_kitnet.py
titli/fe/__init__.py
titli/fe/after_image.py
titli/fe/base_feature_extractor.py
titli/fe/corClust.py
titli/ids/__init__.py
titli/ids/ae.py
titli/ids/base_ids.py
titli/ids/icl.py
titli/ids/kitnet.py
titli/ids/lof.py
titli/ids/ocsvm.py
titli/ids/vae.py
titli/utils/__init__.py
titli/utils/data.py
titli/utils/datasets.py
titli/utils/loss.py
titli-0.0.11.dist-info/licenses/LICENSE
titli-0.0.11.dist-info/METADATA
titli-0.0.11.dist-info/WHEEL
titli-0.0.11.dist-info/top_level.txt
titli-0.0.11.dist-info/RECORD
