Metadata-Version: 2.4
Name: titli
Version: 0.0.11
Summary: A library for collection of IDS and tools for evaluating them
Home-page: https://github.com/spg-iitd/titli
Author: Subrat Kumar Swain
Author-email: Subrat Kumar Swain <mailofswainsubrat@gmail.com>
License: MIT
Project-URL: Homepage, https://github.com/spg-iitd/titli
Keywords: ids,adversarial,network,nids
Classifier: Programming Language :: Python :: 3
Classifier: License :: OSI Approved :: MIT License
Classifier: Operating System :: OS Independent
Classifier: Intended Audience :: Developers
Classifier: Intended Audience :: Science/Research
Classifier: Topic :: Scientific/Engineering :: Artificial Intelligence
Classifier: Topic :: Security
Requires-Python: >=3.10
License-File: LICENSE
Requires-Dist: scapy
Requires-Dist: numpy
Requires-Dist: pandas
Requires-Dist: matplotlib
Requires-Dist: scikit-learn
Requires-Dist: scipy
Requires-Dist: tqdm
Provides-Extra: docs
Requires-Dist: sphinx>=8.0.0; extra == "docs"
Requires-Dist: sphinx-rtd-theme>=3.0.0; extra == "docs"
Requires-Dist: sphinx-autodoc-typehints>=3.0.0; extra == "docs"
Dynamic: author
Dynamic: home-page
Dynamic: license-file
Dynamic: requires-python
